{
  "project_info": {
    "project_number": "144502219994",
    "project_id": "nhandienbienso",
    "storage_bucket": "nhandienbienso.appspot.com"
  },
  "client": [
    {
      "client_info": {
        "mobilesdk_app_id": "1:144502219994:android:88efe2baa7e649d25db1e3",
        "android_client_info": {
          "package_name": "com.example.mongodbrealmcourse"
        }
      },
      "oauth_client": [],
      "api_key": [
        {
          "current_key": "AIzaSyCCmYolDN60KNR__nCNp-WBHUq4PcYLSgM"
        }
      ],
      "services": {
        "appinvite_service": {
          "other_platform_oauth_client": []
        }
      }
    }
  ],
  "configuration_version": "1"
}